main.py
report_generate/__init__.py
report_generate/constants.py
report_generate/exeptions.py
report_generate/file_process.py
report_generate/report.py
race_report_2023-0.1.0.dist-info/METADATA
race_report_2023-0.1.0.dist-info/WHEEL
race_report_2023-0.1.0.dist-info/licenses/LICENSE
race_report_2023-0.1.0.dist-info/RECORD
