Metadata-Version: 2.1
Name: race_report_2023
Version: 0.1.0
Summary: Command line tool, printing report
Project-URL: Homepage, https://test.pypi.org/project/race-report-2023/
Author-email: "r.kovtan" <r.kovtan@gmail.com>
License-File: LICENSE
Classifier: License :: OSI Approved :: MIT License
Classifier: Operating System :: OS Independent
Classifier: Programming Language :: Python :: 3
Requires-Python: >=3.8
